cryptoyaml3/.coveragerc
cryptoyaml3/__init__.py
cryptoyaml3/api.py
cryptoyaml3/commands.py
cryptoyaml3/testing.py
cryptoyaml3/tests/conftest.py
cryptoyaml3/tests/test_api.py
cryptoyaml3/tests/data/plaintext.yml
cryptoyaml3/tests/data/secret
cryptoyaml3/tests/data/settings.yml.aes
cryptoyaml3-0.2.1.dist-info/LICENSE
cryptoyaml3-0.2.1.dist-info/METADATA
cryptoyaml3-0.2.1.dist-info/WHEEL
cryptoyaml3-0.2.1.dist-info/entry_points.txt
cryptoyaml3-0.2.1.dist-info/top_level.txt
cryptoyaml3-0.2.1.dist-info/RECORD
