Metadata-Version: 2.1
Name: cryptoyaml3
Version: 0.2.1
Summary: A python library to manage encrypted YAML files.
Home-page: https://github.com/dflupu/cryptoyaml3.git
Author: Senic GmbH
Author-email: tom@senic.com
License: BSD 2-Clause License
Platform: UNKNOWN
Classifier: Programming Language :: Python
Requires-Dist: click
Requires-Dist: PyYAML
Requires-Dist: cryptography
Provides-Extra: development
Requires-Dist: devpi-client ; extra == 'development'
Requires-Dist: docutils ; extra == 'development'
Requires-Dist: pyflakes ; extra == 'development'
Requires-Dist: flake8 ; extra == 'development'
Requires-Dist: mock ; extra == 'development'
Requires-Dist: pbr ; extra == 'development'
Requires-Dist: pdbpp ; extra == 'development'
Requires-Dist: pep8 (<1.6) ; extra == 'development'
Requires-Dist: pytest ; extra == 'development'
Requires-Dist: pytest-cov ; extra == 'development'
Requires-Dist: pytest-flakes ; extra == 'development'
Requires-Dist: pytest-pep8 ; extra == 'development'
Requires-Dist: pytest-sugar ; extra == 'development'
Requires-Dist: repoze.sphinx.autointerface ; extra == 'development'
Requires-Dist: setuptools-git ; extra == 'development'
Requires-Dist: Sphinx ; extra == 'development'
Requires-Dist: tox ; extra == 'development'
